aiopdhttp/__init__.py
aiopdhttp/api_client.py
aiopdhttp/configuration.py
aiopdhttp/rest.py
aiopdhttp/api/__init__.py
aiopdhttp/api/base_api.py
aiopdhttp/api/default_api.py
aiopdhttp/api/environment_api.py
aiopdhttp/api/gripper_api.py
aiopdhttp/api/other_api.py
aiopdhttp/api/pose_api.py
aiopdhttp/api/position_api.py
aiopdhttp/api/robot_api.py
aiopdhttp/api/signals_api.py
aiopdhttp/api/status_api.py
aiopdhttp/api/tool_api.py
aiopdhttp/api/version_api.py
aiopdhttp/models/__init__.py
aiopdhttp/models/box_obstacle.py
aiopdhttp/models/capsule_obstacle.py
aiopdhttp/models/error400.py
aiopdhttp/models/error_emergency503.py
aiopdhttp/models/error_port412.py
aiopdhttp/models/error_pose412.py
aiopdhttp/models/error_position412.py
aiopdhttp/models/failure.py
aiopdhttp/models/failure_level.py
aiopdhttp/models/failure_type.py
aiopdhttp/models/gripper_robot_action.py
aiopdhttp/models/interpolation_type.py
aiopdhttp/models/jogging_acceleration.py
aiopdhttp/models/jogging_acceleration_acceleration.py
aiopdhttp/models/joint_motion_parameters.py
aiopdhttp/models/joint_poses.py
aiopdhttp/models/joint_positions.py
aiopdhttp/models/linear_motion_parameters.py
aiopdhttp/models/linear_poses.py
aiopdhttp/models/linear_positions.py
aiopdhttp/models/motion_status.py
aiopdhttp/models/motion_type.py
aiopdhttp/models/motor_status.py
aiopdhttp/models/obstacle.py
aiopdhttp/models/output_robot_action.py
aiopdhttp/models/plane_obstacle.py
aiopdhttp/models/point.py
aiopdhttp/models/pose.py
aiopdhttp/models/pose_timestamp.py
aiopdhttp/models/position.py
aiopdhttp/models/position_timestamp.py
aiopdhttp/models/recover_state.py
aiopdhttp/models/robot_action.py
aiopdhttp/models/robot_action_type.py
aiopdhttp/models/robot_info.py
aiopdhttp/models/rotation.py
aiopdhttp/models/session.py
aiopdhttp/models/signal.py
aiopdhttp/models/simplified_capsule_obstacle.py
aiopdhttp/models/system_state.py
aiopdhttp/models/tool_info.py
aiopdhttp/models/tool_shape.py
aiopdhttp/models/version.py
aiopdhttp-1.8.4.dist-info/LICENSE
aiopdhttp-1.8.4.dist-info/METADATA
aiopdhttp-1.8.4.dist-info/WHEEL
aiopdhttp-1.8.4.dist-info/top_level.txt
aiopdhttp-1.8.4.dist-info/RECORD
